<?xml version="1.0" encoding="UTF-8" standalone="yes"?>
<events>
    <event alarm="false" description="Default Description" endDate="2019-05-24 00:00:00.0" id="1" startDate="2019-05-24 00:00:00.0" title="Default Title"/>
    <event alarm="false" description="Default Description" endDate="2019-05-24 00:00:00.0" id="2" startDate="2019-05-24 00:00:00.0" title="Default Title"/>
    <event alarm="false" description="Default Description" endDate="2019-05-24 00:00:00.0" id="3" startDate="2019-05-24 00:00:00.0" title="Default Title"/>
    <event alarm="false" description="Default Description" endDate="2019-05-24 00:00:00.0" id="4" startDate="2019-05-24 00:00:00.0" title="Default Title"/>
    <event alarm="false" description="Default Description" endDate="2019-05-24 00:00:00.0" id="5" startDate="2019-05-24 00:00:00.0" title="Default Title"/>
    <event alarm="false" description="Default Description" endDate="2019-05-24 00:00:00.0" id="6" startDate="2019-05-24 00:00:00.0" title="Default Title"/>
    <event alarm="false" description="Default Description" endDate="2019-05-24 00:00:00.0" id="7" startDate="2019-05-24 00:00:00.0" title="Default Title"/>
    <event alarm="false" description="Default Description" endDate="2019-05-24 00:00:00.0" id="8" startDate="2019-05-24 00:00:00.0" title="Default Title"/>
    <event alarm="false" description="Default Description" endDate="2019-05-24 00:00:00.0" id="9" startDate="2019-05-24 00:00:00.0" title="Default Title"/>
    <event alarm="false" description="Default Description" endDate="2019-05-24 00:00:00.0" id="10" startDate="2019-05-24 00:00:00.0" title="Default Title"/>
</events>
